lgdash/__init__.py
lgdash/cli.py
lgdash/client.py
lgdash/config.py
lgdash/display.py
lgdash/leagues.py
lgdash-0.1.3.dist-info/LICENSE
lgdash-0.1.3.dist-info/METADATA
lgdash-0.1.3.dist-info/WHEEL
lgdash-0.1.3.dist-info/entry_points.txt
lgdash-0.1.3.dist-info/RECORD
