Metadata-Version: 2.1
Name: lgdash
Version: 0.1.3
Summary: A command line tool for displaying live soccer scores and statistics.
Home-page: https://github.com/joypauls/league-dashboard
License: MIT
Keywords: cli,soccer,football,statistics,scores,live
Author: Joy Paulsen
Author-email: joypaulsen3@gmail.com
Requires-Python: >=3.13,<4.0
Classifier: License :: OSI Approved :: MIT License
Classifier: Programming Language :: Python :: 3
Classifier: Programming Language :: Python :: 3.13
Requires-Dist: click (>=8.1.7,<9.0.0)
Requires-Dist: pandas (>=2.2.3,<3.0.0)
Requires-Dist: requests (>=2.32.3,<3.0.0)
Requires-Dist: rich (>=13.9.4,<14.0.0)
Requires-Dist: tzlocal (>=5.2,<6.0)
Project-URL: Repository, https://github.com/joypauls/league-dashboard
